[
	{
		"name": "varjmes",
		"seconds": 65
	},
	{
		"name": "Emma L",
		"seconds": 89
	},
	{
		"name": "leaf",
		"seconds": 113
	},
	{
		"name": "Oliver Turner",
		"seconds": 121
	},
	{
		"name": "Lily2point0",
		"seconds": 127
	},
	{
		"name": "Ania",
		"seconds": 129
	},
	{
		"name": "j-sheps",
		"seconds": 130
	},
	{
		"name": "apaleslimghost",
		"seconds": 132
	},
	{
		"name": "cb",
		"seconds": 132
	},
	{
		"name": "Rowan M",
		"seconds": 227
	},
	{
		"name": "Nick Ramsbottom",
		"seconds": 411
	},
	{
		"name": "arjun137",
		"seconds": null
	},
	{
		"name": "binaryberry",
		"seconds": null
	},
	{
		"name": "itsalex",
		"seconds": null
	},
	{
		"name": "joelcarr",
		"seconds": null
	}
]