[
	{
		"name": "Emma L",
		"scrapeTime": "2022-06-17T06:37:31.948Z",
		"seconds": 30
	},
	{
		"name": "ivo",
		"scrapeTime": "2022-06-17T08:37:17.660Z",
		"seconds": 37
	},
	{
		"name": "Rowan M",
		"scrapeTime": "2022-06-17T13:40:20.260Z",
		"seconds": 39
	},
	{
		"name": "j-sheps",
		"scrapeTime": "2022-06-17T07:32:45.163Z",
		"seconds": 40
	},
	{
		"name": "Lily2point0",
		"scrapeTime": "2022-06-17T07:02:32.716Z",
		"seconds": 70
	},
	{
		"name": "binaryberry",
		"scrapeTime": "2022-06-17T05:33:47.314Z",
		"seconds": 99
	},
	{
		"name": "joelcarr",
		"scrapeTime": "2022-06-17T08:02:36.331Z",
		"seconds": 100
	},
	{
		"name": "Ania",
		"scrapeTime": "2022-06-17T08:37:17.660Z",
		"seconds": 103
	},
	{
		"name": "Alice Bartlett",
		"scrapeTime": null,
		"seconds": null
	},
	{
		"name": "apaleslimghost",
		"scrapeTime": null,
		"seconds": null
	},
	{
		"name": "arjun137",
		"scrapeTime": null,
		"seconds": null
	},
	{
		"name": "cb",
		"scrapeTime": null,
		"seconds": null
	},
	{
		"name": "itsalex",
		"scrapeTime": null,
		"seconds": null
	},
	{
		"name": "JRedondo",
		"scrapeTime": null,
		"seconds": null
	},
	{
		"name": "leaf",
		"scrapeTime": null,
		"seconds": null
	},
	{
		"name": "Nick Ramsbottom",
		"scrapeTime": null,
		"seconds": null
	},
	{
		"name": "Oliver Turner",
		"scrapeTime": null,
		"seconds": null
	},
	{
		"name": "Otherowan",
		"scrapeTime": null,
		"seconds": null
	},
	{
		"name": "varjmes",
		"scrapeTime": null,
		"seconds": null
	}
]