[
	{
		"name": "Emma L",
		"scrapeTime": "2022-06-25T06:36:20.809Z",
		"seconds": 54
	},
	{
		"name": "itsalex",
		"scrapeTime": "2022-06-25T07:02:09.607Z",
		"seconds": 56
	},
	{
		"name": "Alice Bartlett",
		"scrapeTime": "2022-06-25T06:02:19.322Z",
		"seconds": 95
	},
	{
		"name": "apaleslimghost",
		"scrapeTime": "2022-06-25T07:32:09.602Z",
		"seconds": 124
	},
	{
		"name": "binaryberry",
		"scrapeTime": "2022-06-25T07:32:09.602Z",
		"seconds": 155
	},
	{
		"name": "Lily2point0",
		"scrapeTime": "2022-06-25T08:02:32.075Z",
		"seconds": 173
	},
	{
		"name": "Ania",
		"scrapeTime": null,
		"seconds": null
	},
	{
		"name": "arjun137",
		"scrapeTime": null,
		"seconds": null
	},
	{
		"name": "cb",
		"scrapeTime": null,
		"seconds": null
	},
	{
		"name": "ivo",
		"scrapeTime": null,
		"seconds": null
	},
	{
		"name": "j-sheps",
		"scrapeTime": null,
		"seconds": null
	},
	{
		"name": "joelcarr",
		"scrapeTime": null,
		"seconds": null
	},
	{
		"name": "JRedondo",
		"scrapeTime": null,
		"seconds": null
	},
	{
		"name": "leaf",
		"scrapeTime": null,
		"seconds": null
	},
	{
		"name": "Nick Ramsbottom",
		"scrapeTime": null,
		"seconds": null
	},
	{
		"name": "Oliver Turner",
		"scrapeTime": null,
		"seconds": null
	},
	{
		"name": "Otherowan",
		"scrapeTime": null,
		"seconds": null
	},
	{
		"name": "Rowan M",
		"scrapeTime": null,
		"seconds": null
	},
	{
		"name": "varjmes",
		"scrapeTime": null,
		"seconds": null
	}
]