[
	{
		"name": "Emma L",
		"scrapeTime": "2022-02-04T08:02:12.083Z",
		"seconds": 54
	},
	{
		"name": "Lily2point0",
		"scrapeTime": "2022-02-04T08:02:12.083Z",
		"seconds": 110
	},
	{
		"name": "Nick Ramsbottom",
		"scrapeTime": "2022-02-04T06:02:02.674Z",
		"seconds": 132
	},
	{
		"name": "apaleslimghost",
		"scrapeTime": "2022-02-04T07:31:46.963Z",
		"seconds": 141
	},
	{
		"name": "joelcarr",
		"scrapeTime": "2022-02-04T08:32:00.440Z",
		"seconds": 209
	},
	{
		"name": "Alice Bartlett",
		"scrapeTime": null,
		"seconds": null
	},
	{
		"name": "Ania",
		"scrapeTime": null,
		"seconds": null
	},
	{
		"name": "arjun137",
		"scrapeTime": null,
		"seconds": null
	},
	{
		"name": "binaryberry",
		"scrapeTime": null,
		"seconds": null
	},
	{
		"name": "cb",
		"scrapeTime": null,
		"seconds": null
	},
	{
		"name": "itsalex",
		"scrapeTime": null,
		"seconds": null
	},
	{
		"name": "ivo",
		"scrapeTime": null,
		"seconds": null
	},
	{
		"name": "j-sheps",
		"scrapeTime": null,
		"seconds": null
	},
	{
		"name": "leaf",
		"scrapeTime": null,
		"seconds": null
	},
	{
		"name": "Oliver Turner",
		"scrapeTime": null,
		"seconds": null
	},
	{
		"name": "Otherowan",
		"scrapeTime": null,
		"seconds": null
	},
	{
		"name": "Rowan M",
		"scrapeTime": null,
		"seconds": null
	},
	{
		"name": "varjmes",
		"scrapeTime": null,
		"seconds": null
	}
]