[
	{
		"name": "alexmuller",
		"scrapeTime": "2024-04-15T06:02:07.148Z",
		"seconds": 24
	},
	{
		"name": "Emma L",
		"scrapeTime": "2024-04-15T06:31:46.012Z",
		"seconds": 28
	},
	{
		"name": "j-sheps",
		"scrapeTime": "2024-04-14T23:10:53.079Z",
		"seconds": 33
	},
	{
		"name": "emC",
		"scrapeTime": "2024-04-15T13:02:15.690Z",
		"seconds": 34
	},
	{
		"name": "Lily2point0",
		"scrapeTime": "2024-04-15T08:02:12.275Z",
		"seconds": 36
	},
	{
		"name": "ivo",
		"scrapeTime": "2024-04-15T08:32:26.947Z",
		"seconds": 38
	},
	{
		"name": "Otherowan",
		"scrapeTime": "2024-04-15T09:01:58.998Z",
		"seconds": 38
	},
	{
		"name": "binaryberry",
		"scrapeTime": "2024-04-15T03:37:55.506Z",
		"seconds": 81
	},
	{
		"name": "Alice Bartlett",
		"scrapeTime": null,
		"seconds": null
	},
	{
		"name": "Ania",
		"scrapeTime": null,
		"seconds": null
	},
	{
		"name": "apaleslimghost",
		"scrapeTime": null,
		"seconds": null
	},
	{
		"name": "arjun137",
		"scrapeTime": null,
		"seconds": null
	},
	{
		"name": "cb",
		"scrapeTime": null,
		"seconds": null
	},
	{
		"name": "ellejay",
		"scrapeTime": null,
		"seconds": null
	},
	{
		"name": "itsalex",
		"scrapeTime": null,
		"seconds": null
	},
	{
		"name": "joelcarr",
		"scrapeTime": null,
		"seconds": null
	},
	{
		"name": "JRedondo",
		"scrapeTime": null,
		"seconds": null
	},
	{
		"name": "leaf",
		"scrapeTime": null,
		"seconds": null
	},
	{
		"name": "Nick Ramsbottom",
		"scrapeTime": null,
		"seconds": null
	},
	{
		"name": "Oliver Turner",
		"scrapeTime": null,
		"seconds": null
	},
	{
		"name": "Rowan M",
		"scrapeTime": null,
		"seconds": null
	},
	{
		"name": "sal",
		"scrapeTime": null,
		"seconds": null
	},
	{
		"name": "varjmes",
		"scrapeTime": null,
		"seconds": null
	}
]